spotlight/__init__.py
spotlight/api/__init__.py
spotlight/api/model.py
spotlight/api/auth/__init__.py
spotlight/api/auth/__util.py
spotlight/api/auth/asynchronous.py
spotlight/api/auth/synchronous.py
spotlight/api/job/__init__.py
spotlight/api/job/__util.py
spotlight/api/job/asynchronous.py
spotlight/api/job/model.py
spotlight/api/job/synchronous.py
spotlight/api/job/view/__init__.py
spotlight/api/job/view/__util.py
spotlight/api/job/view/asynchronous.py
spotlight/api/job/view/model.py
spotlight/api/job/view/synchronous.py
spotlight/api/organization/__init__.py
spotlight/api/organization/__util.py
spotlight/api/organization/asynchronous.py
spotlight/api/organization/model.py
spotlight/api/organization/synchronous.py
spotlight/api/organization/user/__init__.py
spotlight/api/organization/user/__util.py
spotlight/api/organization/user/asynchronous.py
spotlight/api/organization/user/enum.py
spotlight/api/organization/user/model.py
spotlight/api/organization/user/synchronous.py
spotlight/api/organization/view/__init__.py
spotlight/api/organization/view/__util.py
spotlight/api/organization/view/asynchronous.py
spotlight/api/organization/view/model.py
spotlight/api/organization/view/synchronous.py
spotlight/api/rule/__init__.py
spotlight/api/rule/__util.py
spotlight/api/rule/asynchronous.py
spotlight/api/rule/model.py
spotlight/api/rule/synchronous.py
spotlight/api/tag/__init__.py
spotlight/api/tag/__util.py
spotlight/api/tag/asynchronous.py
spotlight/api/tag/model.py
spotlight/api/tag/synchronous.py
spotlight/api/tag/view/__init__.py
spotlight/api/tag/view/__util.py
spotlight/api/tag/view/asynchronous.py
spotlight/api/tag/view/model.py
spotlight/api/tag/view/synchronous.py
spotlight/core/__init__.py
spotlight/core/common/__init__.py
spotlight/core/common/base.py
spotlight/core/common/base_enum.py
spotlight/core/common/config.py
spotlight/core/common/enum.py
spotlight/core/common/errors.py
spotlight/core/common/function.py
spotlight/core/common/type.py
spotlight_dev-0.0.1b9.dist-info/METADATA
spotlight_dev-0.0.1b9.dist-info/WHEEL
spotlight_dev-0.0.1b9.dist-info/top_level.txt
spotlight_dev-0.0.1b9.dist-info/RECORD
