Metadata-Version: 2.1
Name: spotlight-dev
Version: 0.0.1b9
Summary: Spotlight Python SDK
Home-page: https://alpha.dev
Author: Spotlight
Author-email: hello@spotlight.dev
License: UNKNOWN
Platform: UNKNOWN
Classifier: Programming Language :: Python :: 3
Classifier: Operating System :: OS Independent
Requires-Python: >=3.7
Requires-Dist: aiocache (>=0.12.1)
Requires-Dist: aiohttp (>=3.8.4)
Requires-Dist: asyncstdlib (>=3.10.7)
Requires-Dist: backoff (>=2.2.1)
Requires-Dist: cachetools (>=5.3.0)
Requires-Dist: duckdb (>=0.7.1)
Requires-Dist: pandas (>=2.0.1)
Requires-Dist: pydantic (>=1.10.7)
Requires-Dist: pydash (>=7.0.3)
Requires-Dist: requests (==2.28.1)
Requires-Dist: trycast (>=1.0.0)
